cammy/__init__.py
cammy/__main__.py
cammy/capture.py
cammy/cli.py
cammy/gif.py
cammy/session.py
cammy/utils.py
cammy-0.2.1.dist-info/METADATA
cammy-0.2.1.dist-info/WHEEL
cammy-0.2.1.dist-info/entry_points.txt
cammy-0.2.1.dist-info/top_level.txt
cammy-0.2.1.dist-info/RECORD
