Metadata-Version: 2.4
Name: cammy
Version: 0.2.1
Summary: AI's camera - Multi-desktop screenshot capture with MCP server for AI agents
Author-email: Yusuke Watanabe <Yusuke.Watanabe@scitex.ai>
License: MIT
Project-URL: Homepage, https://github.com/ywatanabe1989/cammy
Project-URL: Repository, https://github.com/ywatanabe1989/cammy
Keywords: screenshot,screen-capture,wsl,windows,monitoring,automation,ai-vision
Classifier: Development Status :: 3 - Alpha
Classifier: Intended Audience :: Developers
Classifier: Topic :: Software Development :: Libraries :: Python Modules
Classifier: Topic :: Multimedia :: Graphics :: Capture :: Screen Capture
Classifier: License :: OSI Approved :: MIT License
Classifier: Programming Language :: Python :: 3
Classifier: Programming Language :: Python :: 3.7
Classifier: Programming Language :: Python :: 3.8
Classifier: Programming Language :: Python :: 3.9
Classifier: Programming Language :: Python :: 3.10
Classifier: Programming Language :: Python :: 3.11
Classifier: Operating System :: Microsoft :: Windows
Classifier: Operating System :: POSIX :: Linux
Requires-Python: >=3.7
Requires-Dist: fastmcp>=2.0.0
Requires-Dist: mss>=6.0.0
Requires-Dist: Pillow>=9.0.0
Provides-Extra: browser
Requires-Dist: playwright>=1.40.0; extra == "browser"
Provides-Extra: dev
Requires-Dist: pytest>=7.0.0; extra == "dev"
Requires-Dist: pytest-cov>=4.0.0; extra == "dev"
Requires-Dist: black>=22.0.0; extra == "dev"
Requires-Dist: flake8>=4.0.0; extra == "dev"
Requires-Dist: pre-commit>=3.0.0; extra == "dev"
